crisp_modals/__init__.py
crisp_modals/admin.py
crisp_modals/apps.py
crisp_modals/forms.py
crisp_modals/migrations/__init__.py
crisp_modals/models.py
crisp_modals/static/crisp_modals/modals.js
crisp_modals/static/crisp_modals/modals.min.js
crisp_modals/templates/crisp_modals/confirm.html
crisp_modals/templates/crisp_modals/delete.html
crisp_modals/templates/crisp_modals/form.html
crisp_modals/templates/crisp_modals/modal.html
crisp_modals/templatetags/__init__.py
crisp_modals/templatetags/crisp_modals.py
crisp_modals/tests.py
crisp_modals/views.py
django_crisp_modals-2026.1.0.dist-info/METADATA
django_crisp_modals-2026.1.0.dist-info/WHEEL
django_crisp_modals-2026.1.0.dist-info/licenses/LICENSE
django_crisp_modals-2026.1.0.dist-info/RECORD
