Metadata-Version: 2.4
Name: django-crisp-modals
Version: 2026.1.0
Summary: Django Crispy Forms inside Bootstrap Modals
License-Expression: MIT
License-File: LICENSE
Author: Michel Fodje
Author-email: michel4j@gmail.com
Requires-Python: >=3.12
Classifier: Environment :: Web Environment
Classifier: Framework :: Django
Classifier: Intended Audience :: Developers
Classifier: Operating System :: OS Independent
Classifier: License :: OSI Approved :: MIT License
Classifier: Programming Language :: Python :: 3
Classifier: Topic :: Internet :: WWW/HTTP
Classifier: Topic :: Internet :: WWW/HTTP :: Dynamic Content
Classifier: Topic :: Software Development :: Libraries :: Application Frameworks
Classifier: Topic :: Software Development :: Libraries :: Python Modules
Requires-Dist: crispy-bootstrap5 (>=2024.10)
Requires-Dist: django (>=5.2.11,<7.0.0)
Requires-Dist: django-crispy-forms (>=2.3)
Requires-Dist: pyyaml (>=6.0.2,<7.0.0)
Project-URL: Homepage, https://github.com/michel4j/django-crisp-modals
Project-URL: Issues, https://github.com/michel4j/django-crisp-modals/issues
